MANIFEST.in
README.md
pyproject.toml
setup.py
amuse_nbody6xx.egg-info/PKG-INFO
amuse_nbody6xx.egg-info/SOURCES.txt
amuse_nbody6xx.egg-info/dependency_links.txt
amuse_nbody6xx.egg-info/requires.txt
amuse_nbody6xx.egg-info/top_level.txt
src/amuse/community/nbody6xx/Makefile
src/amuse/community/nbody6xx/__init__.py
src/amuse/community/nbody6xx/_version.py
src/amuse/community/nbody6xx/common6.h
src/amuse/community/nbody6xx/debug.py
src/amuse/community/nbody6xx/interface.f90
src/amuse/community/nbody6xx/interface.py
src/amuse/community/nbody6xx/interface_new.py
src/amuse/community/nbody6xx/params.h
src/amuse/community/nbody6xx/phigrape.py
src/amuse/community/nbody6xx/src/Makefile
src/amuse/community/nbody6xx/src/absorb.f
src/amuse/community/nbody6xx/src/adjust.F
src/amuse/community/nbody6xx/src/assess.f
src/amuse/community/nbody6xx/src/bindat.f
src/amuse/community/nbody6xx/src/binev.f
src/amuse/community/nbody6xx/src/binout.f
src/amuse/community/nbody6xx/src/binpop.F
src/amuse/community/nbody6xx/src/block.f
src/amuse/community/nbody6xx/src/bodies.f
src/amuse/community/nbody6xx/src/brake.f
src/amuse/community/nbody6xx/src/brake2.f
src/amuse/community/nbody6xx/src/brake3.f
src/amuse/community/nbody6xx/src/bsetid.f
src/amuse/community/nbody6xx/src/cfuncs.f
src/amuse/community/nbody6xx/src/chain.f
src/amuse/community/nbody6xx/src/chaos.f
src/amuse/community/nbody6xx/src/chaos0.f
src/amuse/community/nbody6xx/src/chaos2.f
src/amuse/community/nbody6xx/src/chdata.f
src/amuse/community/nbody6xx/src/check.f
src/amuse/community/nbody6xx/src/check3.f
src/amuse/community/nbody6xx/src/checkl.f
src/amuse/community/nbody6xx/src/chfind.f
src/amuse/community/nbody6xx/src/chfirr.f
src/amuse/community/nbody6xx/src/chinit.f
src/amuse/community/nbody6xx/src/chlist.f
src/amuse/community/nbody6xx/src/chmod.f
src/amuse/community/nbody6xx/src/chpert.f
src/amuse/community/nbody6xx/src/chpot.f
src/amuse/community/nbody6xx/src/chrect.f
src/amuse/community/nbody6xx/src/chstab.f
src/amuse/community/nbody6xx/src/chterm.f
src/amuse/community/nbody6xx/src/clint.f
src/amuse/community/nbody6xx/src/cloud.f
src/amuse/community/nbody6xx/src/cloud0.f
src/amuse/community/nbody6xx/src/cmbody.f
